Metadata-Version: 2.1
Name: psa
Version: 0.1.0
Summary: Predictable subspace analysis
Home-page: https://github.com/wesselb/psa
Author: Wessel Bruinsma
Author-email: wessel.p.bruinsma@gmail.com
License: MIT
Platform: UNKNOWN
Requires-Python: >=3.6
